[{"inputs": [], "stateMutability": "nonpayable", "type": "constructor"}, {"inputs": [{"internalType": "string", "name": "certificateNumber", "type": "string"}], "name": "getCertificate", "outputs": [{"internalType": "string", "name": "", "type": "string"}, {"internalType": "string", "name": "", "type": "string"}, {"internalType": "string", "name": "", "type": "string"}, {"internalType": "string", "name": "", "type": "string"}, {"internalType": "string", "name": "", "type": "string"}, {"internalType": "string", "name": "", "type": "string"}, {"internalType": "string", "name": "", "type": "string"}, {"internalType": "string", "name": "", "type": "string"}, {"internalType": "string", "name": "", "type": "string"}, {"internalType": "string", "name": "", "type": "string"}], "stateMutability": "view", "type": "function"}, {"inputs": [{"internalType": "string", "name": "certificateNumber", "type": "string"}, {"internalType": "string", "name": "studentName", "type": "string"}, {"internalType": "string", "name": "rollNumber", "type": "string"}, {"internalType": "string", "name": "degree", "type": "string"}, {"internalType": "string", "name": "branch", "type": "string"}, {"internalType": "string", "name": "graduationYear", "type": "string"}, {"internalType": "string", "name": "college", "type": "string"}, {"internalType": "string", "name": "university", "type": "string"}, {"internalType": "string", "name": "cgpa", "type": "string"}, {"internalType": "string", "name": "dateOfIssue", "type": "string"}], "name": "issueCertificate", "outputs": [], "stateMutability": "nonpayable", "type": "function"}, {"inputs": [], "name": "issuer", "outputs": [{"internalType": "address", "name": "", "type": "address"}], "stateMutability": "view", "type": "function"}]